odoo/addons/sale_payment_sheet/README.rst
odoo/addons/sale_payment_sheet/__init__.py
odoo/addons/sale_payment_sheet/__manifest__.py
odoo/addons/sale_payment_sheet/i18n/es.po
odoo/addons/sale_payment_sheet/i18n/it.po
odoo/addons/sale_payment_sheet/i18n/sale_payment_sheet.pot
odoo/addons/sale_payment_sheet/models/__init__.py
odoo/addons/sale_payment_sheet/models/res_users.py
odoo/addons/sale_payment_sheet/models/sale_payment_sheet.py
odoo/addons/sale_payment_sheet/readme/CONFIGURE.md
odoo/addons/sale_payment_sheet/readme/CONTRIBUTORS.md
odoo/addons/sale_payment_sheet/readme/DESCRIPTION.md
odoo/addons/sale_payment_sheet/readme/USAGE.md
odoo/addons/sale_payment_sheet/report/report_sale_payment_sheet_summary.xml
odoo/addons/sale_payment_sheet/report/sale_payment_sheet_report.xml
odoo/addons/sale_payment_sheet/security/ir.model.access.csv
odoo/addons/sale_payment_sheet/security/security.xml
odoo/addons/sale_payment_sheet/static/description/icon.png
odoo/addons/sale_payment_sheet/static/description/index.html
odoo/addons/sale_payment_sheet/tests/__init__.py
odoo/addons/sale_payment_sheet/tests/test_sale_payment_sheet.py
odoo/addons/sale_payment_sheet/views/res_users_views.xml
odoo/addons/sale_payment_sheet/views/sale_payment_sheet_menu.xml
odoo/addons/sale_payment_sheet/views/sale_payment_sheet_views.xml
odoo/addons/sale_payment_sheet/wizards/__init__.py
odoo/addons/sale_payment_sheet/wizards/sale_invoice_payment.py
odoo/addons/sale_payment_sheet/wizards/sale_invoice_payment_view.xml
odoo_addon_sale_payment_sheet-17.0.1.0.0.2.dist-info/METADATA
odoo_addon_sale_payment_sheet-17.0.1.0.0.2.dist-info/WHEEL
odoo_addon_sale_payment_sheet-17.0.1.0.0.2.dist-info/top_level.txt
odoo_addon_sale_payment_sheet-17.0.1.0.0.2.dist-info/RECORD
